README.md
setup.py
bin/mock-mysql
mock_mysql.egg-info/PKG-INFO
mock_mysql.egg-info/SOURCES.txt
mock_mysql.egg-info/dependency_links.txt
mock_mysql.egg-info/top_level.txt
mockmysql/__init__.py