Metadata-Version: 1.2
Name: mock-mysql
Version: 0.0.2
Summary: mysqld 服务端模板程序
Home-page: UNKNOWN
Author: Neeky
Author-email: neeky@live.com
Maintainer: Neeky
Maintainer-email: neeky@live.com
License: UNKNOWN
Platform: UNKNOWN
Requires-Python: >=3.8.*
